warpdata/__init__.py
warpdata/compat.py
warpdata/addons/__init__.py
warpdata/addons/builder.py
warpdata/addons/embedding_space.py
warpdata/addons/publish.py
warpdata/api/__init__.py
warpdata/api/dataset.py
warpdata/artifacts/__init__.py
warpdata/artifacts/index.py
warpdata/artifacts/resolver.py
warpdata/artifacts/tar/__init__.py
warpdata/artifacts/tar/index_builder.py
warpdata/artifacts/tar/reader.py
warpdata/cache/__init__.py
warpdata/cache/blob_cache.py
warpdata/cache/context.py
warpdata/catalog/__init__.py
warpdata/catalog/cache.py
warpdata/catalog/resolver.py
warpdata/catalog/store.py
warpdata/catalog/stores/__init__.py
warpdata/catalog/stores/chain.py
warpdata/catalog/stores/file.py
warpdata/catalog/stores/http.py
warpdata/catalog/stores/s3.py
warpdata/cli/__init__.py
warpdata/cli/main.py
warpdata/cli/ui.py
warpdata/cli/commands/__init__.py
warpdata/cli/commands/cache.py
warpdata/cli/commands/cat.py
warpdata/cli/commands/config.py
warpdata/cli/commands/doctor.py
warpdata/cli/commands/embeddings.py
warpdata/cli/commands/head.py
warpdata/cli/commands/info.py
warpdata/cli/commands/ingest.py
warpdata/cli/commands/init.py
warpdata/cli/commands/inspect.py
warpdata/cli/commands/link.py
warpdata/cli/commands/ls.py
warpdata/cli/commands/publish.py
warpdata/cli/commands/register.py
warpdata/cli/commands/schema.py
warpdata/cli/commands/stream.py
warpdata/cli/commands/sync.py
warpdata/cli/commands/unregister.py
warpdata/cli/commands/warm.py
warpdata/config/__init__.py
warpdata/config/backends.py
warpdata/config/settings.py
warpdata/engines/__init__.py
warpdata/engines/duckdb.py
warpdata/ingest/__init__.py
warpdata/ingest/base.py
warpdata/ingest/csv_files.py
warpdata/ingest/imagefolder.py
warpdata/ingest/paired.py
warpdata/manifest/__init__.py
warpdata/manifest/canon.py
warpdata/manifest/model.py
warpdata/manifest/validate.py
warpdata/prefetch/__init__.py
warpdata/prefetch/planners.py
warpdata/prefetch/queue.py
warpdata/prefetch/scheduler.py
warpdata/publish/__init__.py
warpdata-3.0.27.dist-info/METADATA
warpdata-3.0.27.dist-info/WHEEL
warpdata-3.0.27.dist-info/entry_points.txt
warpdata-3.0.27.dist-info/RECORD
